sisy/__init__.py
sisy/admin.py
sisy/apps.py
sisy/consumers.py
sisy/models.py
sisy/routing.py
sisy/signals.py
sisy/tests.py
sisy/views.py
sisy/management/__init__.py
sisy/management/commands/__init__.py
sisy/management/commands/sisy_heartbeat.py
sisy/migrations/0001_initial.py
sisy/migrations/__init__.py
sisy-1.0b3.dist-info/DESCRIPTION.rst
sisy-1.0b3.dist-info/METADATA
sisy-1.0b3.dist-info/RECORD
sisy-1.0b3.dist-info/WHEEL
sisy-1.0b3.dist-info/metadata.json
sisy-1.0b3.dist-info/top_level.txt
