Metadata-Version: 2.0
Name: sisy
Version: 1.0b3
Summary: A lightweight repeating task runner app for Django
Home-page: https://github.com/phoikoi/sisy
Author: Peter Hull
Author-email: z8kflt@gmail.com
License: MIT
Keywords: django,channels,cron,croniter,background-tasks
Platform: UNKNOWN
Classifier: Development Status :: 4 - Beta
Classifier: Intended Audience :: Developers
Classifier: License :: OSI Approved :: MIT License
Classifier: Programming Language :: Python :: 3 :: Only
Classifier: Programming Language :: Python :: 3.6
Requires-Python: >=3.6
Requires-Dist: django (>=1.11)
Requires-Dist: channels
Requires-Dist: croniter
Requires-Dist: arrow
Requires-Dist: pytz
